flask_tailwind/__init__.py
flask_tailwind/cli.py
flask_tailwind/extension.py
flask_tailwind/npm.py
flask_tailwind/starter/.gitignore
flask_tailwind/starter/bs.config.js
flask_tailwind/starter/package.json
flask_tailwind/starter/postcss.config.js
flask_tailwind/starter/src/styles.css
flask_tailwind/starter/tailwind.config.js
flask_tailwind/tags.py
flask_tailwind-0.2.1.dist-info/LICENSE
flask_tailwind-0.2.1.dist-info/WHEEL
flask_tailwind-0.2.1.dist-info/entry_points.txt
flask_tailwind-0.2.1.dist-info/METADATA
flask_tailwind-0.2.1.dist-info/RECORD
