Metadata-Version: 2.1
Name: flask-tailwind
Version: 0.2.1
Summary: Flask+Tailwind integration.
Home-page: https://github.com/abilian/flask-tailwind
Author: Abilian SAS
Author-email: contact@abilian.com
Requires-Python: >=3.9,<4
Classifier: Development Status :: 3 - Alpha
Classifier: Intended Audience :: Developers
Classifier: Natural Language :: English
Classifier: Programming Language :: Python :: 3
Classifier: Programming Language :: Python :: 3.9
Classifier: Programming Language :: Python :: 3.10
Classifier: Programming Language :: Python :: 3.11
Classifier: Programming Language :: Python :: 3
Classifier: Programming Language :: Python :: 3.10
Classifier: Programming Language :: Python :: 3.11
Classifier: Programming Language :: Python :: 3.9
Requires-Dist: Flask (>=2,<3)
